openapi_apollo_client/__init__.py
openapi_apollo_client/apollo_client.py
py_openapi_apollo_client/__init__.py
py_openapi_apollo_client/apollo_client.py
py_openapi_apollo_client-1.0.1.dist-info/METADATA
py_openapi_apollo_client-1.0.1.dist-info/WHEEL
py_openapi_apollo_client-1.0.1.dist-info/top_level.txt
py_openapi_apollo_client-1.0.1.dist-info/RECORD
