Metadata-Version: 2.1
Name: py-openapi-apollo-client
Version: 1.0.1
Summary: python-apollo客户端封装
Home-page: https://github.com/longweiqiang/py_openapi_apollo_client
Author: Weiqiang.long
License: UNKNOWN
Platform: UNKNOWN
Classifier: Programming Language :: Python :: 3
Classifier: License :: OSI Approved :: MIT License
Classifier: Operating System :: OS Independent
